odoo/addons/maintenance_product/README.rst
odoo/addons/maintenance_product/__init__.py
odoo/addons/maintenance_product/__manifest__.py
odoo/addons/maintenance_product/i18n/es.po
odoo/addons/maintenance_product/i18n/it.po
odoo/addons/maintenance_product/i18n/maintenance_product.pot
odoo/addons/maintenance_product/models/__init__.py
odoo/addons/maintenance_product/models/maintenance_equipment.py
odoo/addons/maintenance_product/models/product_category.py
odoo/addons/maintenance_product/models/product_product.py
odoo/addons/maintenance_product/models/product_template.py
odoo/addons/maintenance_product/readme/CONTRIBUTORS.md
odoo/addons/maintenance_product/readme/DESCRIPTION.md
odoo/addons/maintenance_product/readme/USAGE.md
odoo/addons/maintenance_product/static/description/icon.png
odoo/addons/maintenance_product/static/description/index.html
odoo/addons/maintenance_product/tests/__init__.py
odoo/addons/maintenance_product/tests/common.py
odoo/addons/maintenance_product/tests/test_maintenance_product.py
odoo/addons/maintenance_product/views/maintenance_equipment_view.xml
odoo/addons/maintenance_product/views/product_template_view.xml
odoo_addon_maintenance_product-18.0.1.0.2.dist-info/METADATA
odoo_addon_maintenance_product-18.0.1.0.2.dist-info/WHEEL
odoo_addon_maintenance_product-18.0.1.0.2.dist-info/top_level.txt
odoo_addon_maintenance_product-18.0.1.0.2.dist-info/RECORD
